decodablepy/__init__.py
decodablepy/sender.py
decodablepy-0.0.2.dist-info/LICENSE
decodablepy-0.0.2.dist-info/METADATA
decodablepy-0.0.2.dist-info/WHEEL
decodablepy-0.0.2.dist-info/top_level.txt
decodablepy-0.0.2.dist-info/RECORD
